Metadata-Version: 2.2
Name: hello_world-lion3l123
Version: 0.1.0
Summary: Tugas Hello World
Author-email: Lionel Saputra <LionelSaputra22@gmail.com>
License: MIT
